{
  "_collector": {
    "fetched_at": "2026-05-05T02:09:23.123819+00:00",
    "source_index": 78,
    "source_title": "",
    "source_url": "https://www.bilibili.com/video/BV1c43zztE6c"
  },
  "_has_drm": null,
  "_old_archive_ids": [
    "bilibili 114808233921416_part1"
  ],
  "_type": "video",
  "_version": {
    "current_git_head": null,
    "release_git_head": "04d6974f502bbdfaed72c624344f262e30ad9708",
    "repository": "yt-dlp/yt-dlp",
    "version": "2026.03.17"
  },
  "abr": 184.426,
  "acodec": "mp4a.40.2",
  "aspect_ratio": 1.78,
  "asr": null,
  "audio_channels": null,
  "chapters": null,
  "comment_count": 309,
  "description": "-",
  "display_id": "BV1c43zztE6c",
  "duration": 2117.919,
  "duration_string": "35:17",
  "dynamic_range": "SDR",
  "epoch": 1777946963,
  "ext": "mp4",
  "extractor": "BiliBili",
  "extractor_key": "BiliBili",
  "filesize_approx": 104005707,
  "format": "1080P 高清+30280 - audio only",
  "format_id": "100026+30280",
  "format_note": null,
  "formats": [
    {
      "abr": 39.858,
      "acodec": "mp4a.40.5",
      "aspect_ratio": null,
      "audio_ext": "m4a",
      "ext": "m4a",
      "filesize": null,
      "filesize_approx": 10552001,
      "format": "30216 - audio only",
      "format_id": "30216",
      "http_headers": {
        "Accept": "text/html,application/xhtml+xml,application/xml;q=0.9,*/*;q=0.8",
        "Accept-Language": "en-us,en;q=0.5",
        "Referer": "https://www.bilibili.com/video/BV1c43zztE6c",
        "Sec-Fetch-Mode": "navigate",
        "User-Agent": "Mozilla/5.0 (Windows NT 10.0; Win64; x64) AppleWebKit/537.36 (KHTML, like Gecko) Chrome/137.0.0.0 Safari/537.36"
      },
      "protocol": "https",
      "resolution": "audio only",
      "tbr": 39.858,
      "url": "https://upos-hz-mirrorakam.akamaized.net/upgcxcode/50/07/30891180750/30891180750-1-30216.m4s?e=ig8euxZM2rNcNbdlhoNvNC8BqJIzNbfqXBvEqxTEto8BTrNvN0GvT90W5JZMkX_YN0MvXg8gNEV4NC8xNEV4N03eN0B5tZlqNxTEto8BTrNvNeZVuJ10Kj_g2UB02J0mN0B5tZlqNCNEto8BTrNvNC7MTX502C8f2jmMQJ6mqF2fka1mqx6gqj0eN0B599M=&mid=0&nbs=1&uipk=5&gen=playurlv3&os=akam&og=hw&trid=6e6bf5d5356f45b495a7cbdf08b639du&deadline=1777954162&oi=2892325852&platform=pc&upsig=15a750e4a02caa01d2bcc3111905783c&uparams=e,mid,nbs,uipk,gen,os,og,trid,deadline,oi,platform&hdnts=exp=1777954162~hmac=ad4d706b259ab429e45549c8e8490cbb376cbb7154305e0dc29b3054b9d5947d&bvc=vod&nettype=0&bw=39897&qn_dyeid=6e835943d408cfc200c09dcc69f95152&agrr=0&buvid=6CD6DFCE-00AE-BB7F-293A-E3A9A14863F560854infoc&build=0&dl=0&f=u_0_0&orderid=0,2",
      "vbr": 0,
      "vcodec": "none",
      "video_ext": "none"
    },
    {
      "abr": 88.904,
      "acodec": "mp4a.40.2",
      "aspect_ratio": null,
      "audio_ext": "m4a",
      "ext": "m4a",
      "filesize": null,
      "filesize_approx": 23536433,
      "format": "30232 - audio only",
      "format_id": "30232",
      "http_headers": {
        "Accept": "text/html,application/xhtml+xml,application/xml;q=0.9,*/*;q=0.8",
        "Accept-Language": "en-us,en;q=0.5",
        "Referer": "https://www.bilibili.com/video/BV1c43zztE6c",
        "Sec-Fetch-Mode": "navigate",
        "User-Agent": "Mozilla/5.0 (Windows NT 10.0; Win64; x64) AppleWebKit/537.36 (KHTML, like Gecko) Chrome/137.0.0.0 Safari/537.36"
      },
      "protocol": "https",
      "resolution": "audio only",
      "tbr": 88.904,
      "url": "https://upos-hz-mirrorakam.akamaized.net/upgcxcode/50/07/30891180750/30891180750-1-30232.m4s?e=ig8euxZM2rNcNbdlhoNvNC8BqJIzNbfqXBvEqxTEto8BTrNvN0GvT90W5JZMkX_YN0MvXg8gNEV4NC8xNEV4N03eN0B5tZlqNxTEto8BTrNvNeZVuJ10Kj_g2UB02J0mN0B5tZlqNCNEto8BTrNvNC7MTX502C8f2jmMQJ6mqF2fka1mqx6gqj0eN0B599M=&mid=0&deadline=1777954162&oi=2892325852&gen=playurlv3&os=akam&nbs=1&uipk=5&platform=pc&trid=6e6bf5d5356f45b495a7cbdf08b639du&og=hw&upsig=5d3fae7539c4f079fb1ffd5f0c57f156&uparams=e,mid,deadline,oi,gen,os,nbs,uipk,platform,trid,og&hdnts=exp=1777954162~hmac=7ab903ad968e5a2d494d49943ebb15240e6ac117cab1ed930a48f238b3734fa4&bvc=vod&nettype=0&bw=88965&qn_dyeid=6e835943d408cfc200c09dcc69f95152&agrr=0&buvid=6CD6DFCE-00AE-BB7F-293A-E3A9A14863F560854infoc&build=0&dl=0&f=u_0_0&orderid=0,2",
      "vbr": 0,
      "vcodec": "none",
      "video_ext": "none"
    },
    {
      "abr": 184.426,
      "acodec": "mp4a.40.2",
      "aspect_ratio": null,
      "audio_ext": "m4a",
      "ext": "m4a",
      "filesize": null,
      "filesize_approx": 48824916,
      "format": "30280 - audio only",
      "format_id": "30280",
      "http_headers": {
        "Accept": "text/html,application/xhtml+xml,application/xml;q=0.9,*/*;q=0.8",
        "Accept-Language": "en-us,en;q=0.5",
        "Referer": "https://www.bilibili.com/video/BV1c43zztE6c",
        "Sec-Fetch-Mode": "navigate",
        "User-Agent": "Mozilla/5.0 (Windows NT 10.0; Win64; x64) AppleWebKit/537.36 (KHTML, like Gecko) Chrome/137.0.0.0 Safari/537.36"
      },
      "protocol": "https",
      "resolution": "audio only",
      "tbr": 184.426,
      "url": "https://upos-sz-mirrorcosov.bilivideo.com/upgcxcode/50/07/30891180750/30891180750-1-30280.m4s?e=ig8euxZM2rNcNbdlhoNvNC8BqJIzNbfqXBvEqxTEto8BTrNvN0GvT90W5JZMkX_YN0MvXg8gNEV4NC8xNEV4N03eN0B5tZlqNxTEto8BTrNvNeZVuJ10Kj_g2UB02J0mN0B5tZlqNCNEto8BTrNvNC7MTX502C8f2jmMQJ6mqF2fka1mqx6gqj0eN0B599M=&deadline=1777954162&os=cosovbv&og=hw&uipk=5&oi=2892325852&platform=pc&mid=0&nbs=1&gen=playurlv3&trid=6e6bf5d5356f45b495a7cbdf08b639du&upsig=6192f3ffcc65245e82c09d5122621f30&uparams=e,deadline,os,og,uipk,oi,platform,mid,nbs,gen,trid&bvc=vod&nettype=0&bw=184529&qn_dyeid=6e835943d408cfc200c09dcc69f95152&agrr=0&buvid=6CD6DFCE-00AE-BB7F-293A-E3A9A14863F560854infoc&build=0&dl=0&f=u_0_0&orderid=0,2",
      "vbr": 0,
      "vcodec": "none",
      "video_ext": "none"
    },
    {
      "abr": 0,
      "acodec": "none",
      "aspect_ratio": 1.78,
      "audio_ext": "none",
      "dynamic_range": "SDR",
      "ext": "mp4",
      "filesize": null,
      "filesize_approx": 10155686,
      "format": "360P 流畅",
      "format_id": "100046",
      "fps": 30.0,
      "height": 360,
      "http_headers": {
        "Accept": "text/html,application/xhtml+xml,application/xml;q=0.9,*/*;q=0.8",
        "Accept-Language": "en-us,en;q=0.5",
        "Referer": "https://www.bilibili.com/video/BV1c43zztE6c",
        "Sec-Fetch-Mode": "navigate",
        "User-Agent": "Mozilla/5.0 (Windows NT 10.0; Win64; x64) AppleWebKit/537.36 (KHTML, like Gecko) Chrome/137.0.0.0 Safari/537.36"
      },
      "protocol": "https",
      "quality": 16,
      "resolution": "640x360",
      "tbr": 38.361,
      "url": "https://upos-hz-mirrorakam.akamaized.net/upgcxcode/50/07/30891180750/30891180750-1-100046.m4s?e=ig8euxZM2rNcNbdlhoNvNC8BqJIzNbfqXBvEqxTEto8BTrNvN0GvT90W5JZMkX_YN0MvXg8gNEV4NC8xNEV4N03eN0B5tZlqNxTEto8BTrNvNeZVuJ10Kj_g2UB02J0mN0B5tZlqNCNEto8BTrNvNC7MTX502C8f2jmMQJ6mqF2fka1mqx6gqj0eN0B599M=&trid=6e6bf5d5356f45b495a7cbdf08b639du&gen=playurlv3&og=hw&deadline=1777954162&nbs=1&oi=2892325852&platform=pc&os=akam&mid=0&uipk=5&upsig=8531caf625c3a81c7f9b2afcab5b16e8&uparams=e,trid,gen,og,deadline,nbs,oi,platform,os,mid,uipk&hdnts=exp=1777954162~hmac=ac3f6387db1d1a8d532ba3d29b1a27f2cac0bb0b92036a2a2a12b3bb77099c53&bvc=vod&nettype=0&bw=38400&build=0&dl=0&f=u_0_0&qn_dyeid=6e835943d408cfc200c09dcc69f95152&agrr=0&buvid=6CD6DFCE-00AE-BB7F-293A-E3A9A14863F560854infoc&orderid=0,2",
      "vbr": 38.361,
      "vcodec": "avc1.64001E",
      "video_ext": "mp4",
      "width": 640
    },
    {
      "abr": 0,
      "acodec": "none",
      "aspect_ratio": 1.78,
      "audio_ext": "none",
      "dynamic_range": "SDR",
      "ext": "mp4",
      "filesize": null,
      "filesize_approx": 19237587,
      "format": "360P 流畅",
      "format_id": "30011",
      "fps": 30.0,
      "height": 360,
      "http_headers": {
        "Accept": "text/html,application/xhtml+xml,application/xml;q=0.9,*/*;q=0.8",
        "Accept-Language": "en-us,en;q=0.5",
        "Referer": "https://www.bilibili.com/video/BV1c43zztE6c",
        "Sec-Fetch-Mode": "navigate",
        "User-Agent": "Mozilla/5.0 (Windows NT 10.0; Win64; x64) AppleWebKit/537.36 (KHTML, like Gecko) Chrome/137.0.0.0 Safari/537.36"
      },
      "protocol": "https",
      "quality": 16,
      "resolution": "640x360",
      "tbr": 72.666,
      "url": "https://upos-sz-mirrorcosov.bilivideo.com/upgcxcode/50/07/30891180750/30891180750-1-30011.m4s?e=ig8euxZM2rNcNbdlhoNvNC8BqJIzNbfqXBvEqxTEto8BTrNvN0GvT90W5JZMkX_YN0MvXg8gNEV4NC8xNEV4N03eN0B5tZlqNxTEto8BTrNvNeZVuJ10Kj_g2UB02J0mN0B5tZlqNCNEto8BTrNvNC7MTX502C8f2jmMQJ6mqF2fka1mqx6gqj0eN0B599M=&nbs=1&oi=2892325852&platform=pc&trid=6e6bf5d5356f45b495a7cbdf08b639du&gen=playurlv3&mid=0&uipk=5&os=cosovbv&og=cos&deadline=1777954162&upsig=18871014510e31ee9994bc6b0c2d4315&uparams=e,nbs,oi,platform,trid,gen,mid,uipk,os,og,deadline&bvc=vod&nettype=0&bw=72721&dl=0&f=u_0_0&qn_dyeid=6e835943d408cfc200c09dcc69f95152&agrr=0&buvid=6CD6DFCE-00AE-BB7F-293A-E3A9A14863F560854infoc&build=0&orderid=0,2",
      "vbr": 72.666,
      "vcodec": "hev1.1.6.L120.90",
      "video_ext": "mp4",
      "width": 640
    },
    {
      "abr": 0,
      "acodec": "none",
      "aspect_ratio": 1.78,
      "audio_ext": "none",
      "dynamic_range": "SDR",
      "ext": "mp4",
      "filesize": null,
      "filesize_approx": 14303365,
      "format": "360P 流畅",
      "format_id": "100022",
      "fps": 30.0,
      "height": 360,
      "http_headers": {
        "Accept": "text/html,application/xhtml+xml,application/xml;q=0.9,*/*;q=0.8",
        "Accept-Language": "en-us,en;q=0.5",
        "Referer": "https://www.bilibili.com/video/BV1c43zztE6c",
        "Sec-Fetch-Mode": "navigate",
        "User-Agent": "Mozilla/5.0 (Windows NT 10.0; Win64; x64) AppleWebKit/537.36 (KHTML, like Gecko) Chrome/137.0.0.0 Safari/537.36"
      },
      "protocol": "https",
      "quality": 16,
      "resolution": "640x360",
      "tbr": 54.028,
      "url": "https://upos-sz-mirrorcosov.bilivideo.com/upgcxcode/50/07/30891180750/30891180750-1-100022.m4s?e=ig8euxZM2rNcNbdlhoNvNC8BqJIzNbfqXBvEqxTEto8BTrNvN0GvT90W5JZMkX_YN0MvXg8gNEV4NC8xNEV4N03eN0B5tZlqNxTEto8BTrNvNeZVuJ10Kj_g2UB02J0mN0B5tZlqNCNEto8BTrNvNC7MTX502C8f2jmMQJ6mqF2fka1mqx6gqj0eN0B599M=&os=cosovbv&og=cos&mid=0&nbs=1&platform=pc&trid=6e6bf5d5356f45b495a7cbdf08b639du&deadline=1777954162&uipk=5&oi=2892325852&gen=playurlv3&upsig=faf10ee2de46e9b28926787aec2d24ee&uparams=e,os,og,mid,nbs,platform,trid,deadline,uipk,oi,gen&bvc=vod&nettype=0&bw=54074&qn_dyeid=6e835943d408cfc200c09dcc69f95152&agrr=0&buvid=6CD6DFCE-00AE-BB7F-293A-E3A9A14863F560854infoc&build=0&dl=0&f=u_0_0&orderid=0,2",
      "vbr": 54.028,
      "vcodec": "av01.0.00M.10.0.110.01.01.01.0",
      "video_ext": "mp4",
      "width": 640
    },
    {
      "abr": 0,
      "acodec": "none",
      "aspect_ratio": 1.77,
      "audio_ext": "none",
      "dynamic_range": "SDR",
      "ext": "mp4",
      "filesize": null,
      "filesize_approx": 16722558,
      "format": "480P 标清",
      "format_id": "100047",
      "fps": 30.0,
      "height": 480,
      "http_headers": {
        "Accept": "text/html,application/xhtml+xml,application/xml;q=0.9,*/*;q=0.8",
        "Accept-Language": "en-us,en;q=0.5",
        "Referer": "https://www.bilibili.com/video/BV1c43zztE6c",
        "Sec-Fetch-Mode": "navigate",
        "User-Agent": "Mozilla/5.0 (Windows NT 10.0; Win64; x64) AppleWebKit/537.36 (KHTML, like Gecko) Chrome/137.0.0.0 Safari/537.36"
      },
      "protocol": "https",
      "quality": 32,
      "resolution": "852x480",
      "tbr": 63.166,
      "url": "https://upos-sz-mirrorcosov.bilivideo.com/upgcxcode/50/07/30891180750/30891180750-1-100047.m4s?e=ig8euxZM2rNcNbdlhoNvNC8BqJIzNbfqXBvEqxTEto8BTrNvN0GvT90W5JZMkX_YN0MvXg8gNEV4NC8xNEV4N03eN0B5tZlqNxTEto8BTrNvNeZVuJ10Kj_g2UB02J0mN0B5tZlqNCNEto8BTrNvNC7MTX502C8f2jmMQJ6mqF2fka1mqx6gqj0eN0B599M=&platform=pc&deadline=1777954162&uipk=5&trid=6e6bf5d5356f45b495a7cbdf08b639du&mid=0&gen=playurlv3&os=cosovbv&og=hw&nbs=1&oi=2892325852&upsig=76f03cbb9403cbbbb2a2970292f7f1e3&uparams=e,platform,deadline,uipk,trid,mid,gen,os,og,nbs,oi&bvc=vod&nettype=0&bw=63216&buvid=6CD6DFCE-00AE-BB7F-293A-E3A9A14863F560854infoc&build=0&dl=0&f=u_0_0&qn_dyeid=6e835943d408cfc200c09dcc69f95152&agrr=0&orderid=0,2",
      "vbr": 63.166,
      "vcodec": "avc1.64001F",
      "video_ext": "mp4",
      "width": 852
    },
    {
      "abr": 0,
      "acodec": "none",
      "aspect_ratio": 1.77,
      "audio_ext": "none",
      "dynamic_range": "SDR",
      "ext": "mp4",
      "filesize": null,
      "filesize_approx": 28040453,
      "format": "480P 标清",
      "format_id": "30033",
      "fps": 30.0,
      "height": 480,
      "http_headers": {
        "Accept": "text/html,application/xhtml+xml,application/xml;q=0.9,*/*;q=0.8",
        "Accept-Language": "en-us,en;q=0.5",
        "Referer": "https://www.bilibili.com/video/BV1c43zztE6c",
        "Sec-Fetch-Mode": "navigate",
        "User-Agent": "Mozilla/5.0 (Windows NT 10.0; Win64; x64) AppleWebKit/537.36 (KHTML, like Gecko) Chrome/137.0.0.0 Safari/537.36"
      },
      "protocol": "https",
      "quality": 32,
      "resolution": "852x480",
      "tbr": 105.917,
      "url": "https://upos-sz-mirrorcosov.bilivideo.com/upgcxcode/50/07/30891180750/30891180750-1-30033.m4s?e=ig8euxZM2rNcNbdlhoNvNC8BqJIzNbfqXBvEqxTEto8BTrNvN0GvT90W5JZMkX_YN0MvXg8gNEV4NC8xNEV4N03eN0B5tZlqNxTEto8BTrNvNeZVuJ10Kj_g2UB02J0mN0B5tZlqNCNEto8BTrNvNC7MTX502C8f2jmMQJ6mqF2fka1mqx6gqj0eN0B599M=&trid=6e6bf5d5356f45b495a7cbdf08b639du&os=cosovbv&og=ali&mid=0&deadline=1777954162&uipk=5&oi=2892325852&gen=playurlv3&nbs=1&platform=pc&upsig=755542f406d46a20edad20efbf23bb4b&uparams=e,trid,os,og,mid,deadline,uipk,oi,gen,nbs,platform&bvc=vod&nettype=0&bw=105985&agrr=0&buvid=6CD6DFCE-00AE-BB7F-293A-E3A9A14863F560854infoc&build=0&dl=0&f=u_0_0&qn_dyeid=6e835943d408cfc200c09dcc69f95152&orderid=0,2",
      "vbr": 105.917,
      "vcodec": "hev1.1.6.L120.90",
      "video_ext": "mp4",
      "width": 852
    },
    {
      "abr": 0,
      "acodec": "none",
      "aspect_ratio": 1.77,
      "audio_ext": "none",
      "dynamic_range": "SDR",
      "ext": "mp4",
      "filesize": null,
      "filesize_approx": 20095080,
      "format": "480P 标清",
      "format_id": "100023",
      "fps": 30.0,
      "height": 480,
      "http_headers": {
        "Accept": "text/html,application/xhtml+xml,application/xml;q=0.9,*/*;q=0.8",
        "Accept-Language": "en-us,en;q=0.5",
        "Referer": "https://www.bilibili.com/video/BV1c43zztE6c",
        "Sec-Fetch-Mode": "navigate",
        "User-Agent": "Mozilla/5.0 (Windows NT 10.0; Win64; x64) AppleWebKit/537.36 (KHTML, like Gecko) Chrome/137.0.0.0 Safari/537.36"
      },
      "protocol": "https",
      "quality": 32,
      "resolution": "852x480",
      "tbr": 75.905,
      "url": "https://upos-sz-mirrorcosov.bilivideo.com/upgcxcode/50/07/30891180750/30891180750-1-100023.m4s?e=ig8euxZM2rNcNbdlhoNvNC8BqJIzNbfqXBvEqxTEto8BTrNvN0GvT90W5JZMkX_YN0MvXg8gNEV4NC8xNEV4N03eN0B5tZlqNxTEto8BTrNvNeZVuJ10Kj_g2UB02J0mN0B5tZlqNCNEto8BTrNvNC7MTX502C8f2jmMQJ6mqF2fka1mqx6gqj0eN0B599M=&oi=2892325852&og=hw&trid=6e6bf5d5356f45b495a7cbdf08b639du&deadline=1777954162&gen=playurlv3&os=cosovbv&platform=pc&mid=0&nbs=1&uipk=5&upsig=fb8f4639ac8ce7b47ebb1bc6b753ba16&uparams=e,oi,og,trid,deadline,gen,os,platform,mid,nbs,uipk&bvc=vod&nettype=0&bw=75960&qn_dyeid=6e835943d408cfc200c09dcc69f95152&agrr=0&buvid=6CD6DFCE-00AE-BB7F-293A-E3A9A14863F560854infoc&build=0&dl=0&f=u_0_0&orderid=0,2",
      "vbr": 75.905,
      "vcodec": "av01.0.00M.10.0.110.01.01.01.0",
      "video_ext": "mp4",
      "width": 852
    },
    {
      "abr": 0,
      "acodec": "none",
      "aspect_ratio": 1.78,
      "audio_ext": "none",
      "dynamic_range": "SDR",
      "ext": "mp4",
      "filesize": null,
      "filesize_approx": 31113024,
      "format": "720P 准高清",
      "format_id": "100048",
      "fps": 30.0,
      "height": 720,
      "http_headers": {
        "Accept": "text/html,application/xhtml+xml,application/xml;q=0.9,*/*;q=0.8",
        "Accept-Language": "en-us,en;q=0.5",
        "Referer": "https://www.bilibili.com/video/BV1c43zztE6c",
        "Sec-Fetch-Mode": "navigate",
        "User-Agent": "Mozilla/5.0 (Windows NT 10.0; Win64; x64) AppleWebKit/537.36 (KHTML, like Gecko) Chrome/137.0.0.0 Safari/537.36"
      },
      "protocol": "https",
      "quality": 64,
      "resolution": "1280x720",
      "tbr": 117.523,
      "url": "https://upos-sz-mirrorcosov.bilivideo.com/upgcxcode/50/07/30891180750/30891180750-1-100048.m4s?e=ig8euxZM2rNcNbdlhoNvNC8BqJIzNbfqXBvEqxTEto8BTrNvN0GvT90W5JZMkX_YN0MvXg8gNEV4NC8xNEV4N03eN0B5tZlqNxTEto8BTrNvNeZVuJ10Kj_g2UB02J0mN0B5tZlqNCNEto8BTrNvNC7MTX502C8f2jmMQJ6mqF2fka1mqx6gqj0eN0B599M=&deadline=1777954162&uipk=5&os=cosovbv&og=ali&trid=6e6bf5d5356f45b495a7cbdf08b639du&nbs=1&oi=2892325852&platform=pc&gen=playurlv3&mid=0&upsig=ee979df10bdb314e731e6502e1c81223&uparams=e,deadline,uipk,os,og,trid,nbs,oi,platform,gen,mid&bvc=vod&nettype=0&bw=117595&qn_dyeid=6e835943d408cfc200c09dcc69f95152&agrr=0&buvid=6CD6DFCE-00AE-BB7F-293A-E3A9A14863F560854infoc&build=0&dl=0&f=u_0_0&orderid=0,2",
      "vbr": 117.523,
      "vcodec": "avc1.640028",
      "video_ext": "mp4",
      "width": 1280
    },
    {
      "abr": 0,
      "acodec": "none",
      "aspect_ratio": 1.78,
      "audio_ext": "none",
      "dynamic_range": "SDR",
      "ext": "mp4",
      "filesize": null,
      "filesize_approx": 47426030,
      "format": "720P 准高清",
      "format_id": "30066",
      "fps": 30.0,
      "height": 720,
      "http_headers": {
        "Accept": "text/html,application/xhtml+xml,application/xml;q=0.9,*/*;q=0.8",
        "Accept-Language": "en-us,en;q=0.5",
        "Referer": "https://www.bilibili.com/video/BV1c43zztE6c",
        "Sec-Fetch-Mode": "navigate",
        "User-Agent": "Mozilla/5.0 (Windows NT 10.0; Win64; x64) AppleWebKit/537.36 (KHTML, like Gecko) Chrome/137.0.0.0 Safari/537.36"
      },
      "protocol": "https",
      "quality": 64,
      "resolution": "1280x720",
      "tbr": 179.142,
      "url": "https://upos-hz-mirrorakam.akamaized.net/upgcxcode/50/07/30891180750/30891180750-1-30066.m4s?e=ig8euxZM2rNcNbdlhoNvNC8BqJIzNbfqXBvEqxTEto8BTrNvN0GvT90W5JZMkX_YN0MvXg8gNEV4NC8xNEV4N03eN0B5tZlqNxTEto8BTrNvNeZVuJ10Kj_g2UB02J0mN0B5tZlqNCNEto8BTrNvNC7MTX502C8f2jmMQJ6mqF2fka1mqx6gqj0eN0B599M=&deadline=1777954162&nbs=1&oi=2892325852&trid=6e6bf5d5356f45b495a7cbdf08b639du&mid=0&uipk=5&gen=playurlv3&os=akam&og=cos&platform=pc&upsig=03076f2e7ad9665a9be4f1e290eb53ff&uparams=e,deadline,nbs,oi,trid,mid,uipk,gen,os,og,platform&hdnts=exp=1777954162~hmac=d04b673a8cefb82d0981dd25f155e35c4d816adbbdc8d6217b2d1ae4ef193b1a&bvc=vod&nettype=0&bw=179242&build=0&dl=0&f=u_0_0&qn_dyeid=6e835943d408cfc200c09dcc69f95152&agrr=0&buvid=6CD6DFCE-00AE-BB7F-293A-E3A9A14863F560854infoc&orderid=0,2",
      "vbr": 179.142,
      "vcodec": "hev1.1.6.L120.90",
      "video_ext": "mp4",
      "width": 1280
    },
    {
      "abr": 0,
      "acodec": "none",
      "aspect_ratio": 1.78,
      "audio_ext": "none",
      "dynamic_range": "SDR",
      "ext": "mp4",
      "filesize": null,
      "filesize_approx": 32903989,
      "format": "720P 准高清",
      "format_id": "100024",
      "fps": 30.0,
      "height": 720,
      "http_headers": {
        "Accept": "text/html,application/xhtml+xml,application/xml;q=0.9,*/*;q=0.8",
        "Accept-Language": "en-us,en;q=0.5",
        "Referer": "https://www.bilibili.com/video/BV1c43zztE6c",
        "Sec-Fetch-Mode": "navigate",
        "User-Agent": "Mozilla/5.0 (Windows NT 10.0; Win64; x64) AppleWebKit/537.36 (KHTML, like Gecko) Chrome/137.0.0.0 Safari/537.36"
      },
      "protocol": "https",
      "quality": 64,
      "resolution": "1280x720",
      "tbr": 124.288,
      "url": "https://upos-sz-mirrorcosov.bilivideo.com/upgcxcode/50/07/30891180750/30891180750-1-100024.m4s?e=ig8euxZM2rNcNbdlhoNvNC8BqJIzNbfqXBvEqxTEto8BTrNvN0GvT90W5JZMkX_YN0MvXg8gNEV4NC8xNEV4N03eN0B5tZlqNxTEto8BTrNvNeZVuJ10Kj_g2UB02J0mN0B5tZlqNCNEto8BTrNvNC7MTX502C8f2jmMQJ6mqF2fka1mqx6gqj0eN0B599M=&trid=6e6bf5d5356f45b495a7cbdf08b639du&mid=0&nbs=1&uipk=5&oi=2892325852&gen=playurlv3&og=hw&platform=pc&deadline=1777954162&os=cosovbv&upsig=29575ecae57fec67d4230729a257feca&uparams=e,trid,mid,nbs,uipk,oi,gen,og,platform,deadline,os&bvc=vod&nettype=0&bw=124364&qn_dyeid=6e835943d408cfc200c09dcc69f95152&agrr=0&buvid=6CD6DFCE-00AE-BB7F-293A-E3A9A14863F560854infoc&build=0&dl=0&f=u_0_0&orderid=0,2",
      "vbr": 124.288,
      "vcodec": "av01.0.00M.10.0.110.01.01.01.0",
      "video_ext": "mp4",
      "width": 1280
    },
    {
      "abr": 0,
      "acodec": "none",
      "aspect_ratio": 1.78,
      "audio_ext": "none",
      "dynamic_range": "SDR",
      "ext": "mp4",
      "filesize": null,
      "filesize_approx": 45718458,
      "format": "1080P 高清",
      "format_id": "100050",
      "fps": 30.0,
      "height": 1080,
      "http_headers": {
        "Accept": "text/html,application/xhtml+xml,application/xml;q=0.9,*/*;q=0.8",
        "Accept-Language": "en-us,en;q=0.5",
        "Referer": "https://www.bilibili.com/video/BV1c43zztE6c",
        "Sec-Fetch-Mode": "navigate",
        "User-Agent": "Mozilla/5.0 (Windows NT 10.0; Win64; x64) AppleWebKit/537.36 (KHTML, like Gecko) Chrome/137.0.0.0 Safari/537.36"
      },
      "protocol": "https",
      "quality": 80,
      "resolution": "1920x1080",
      "tbr": 172.692,
      "url": "https://upos-sz-mirrorcosov.bilivideo.com/upgcxcode/50/07/30891180750/30891180750-1-100050.m4s?e=ig8euxZM2rNcNbdlhoNvNC8BqJIzNbfqXBvEqxTEto8BTrNvN0GvT90W5JZMkX_YN0MvXg8gNEV4NC8xNEV4N03eN0B5tZlqNxTEto8BTrNvNeZVuJ10Kj_g2UB02J0mN0B5tZlqNCNEto8BTrNvNC7MTX502C8f2jmMQJ6mqF2fka1mqx6gqj0eN0B599M=&mid=0&deadline=1777954162&nbs=1&oi=2892325852&trid=6e6bf5d5356f45b495a7cbdf08b639du&og=cos&uipk=5&platform=pc&gen=playurlv3&os=cosovbv&upsig=0adec4e0087b6980e66750ea7363ab4c&uparams=e,mid,deadline,nbs,oi,trid,og,uipk,platform,gen,os&bvc=vod&nettype=0&bw=172788&qn_dyeid=6e835943d408cfc200c09dcc69f95152&agrr=0&buvid=6CD6DFCE-00AE-BB7F-293A-E3A9A14863F560854infoc&build=0&dl=0&f=u_0_0&orderid=0,2",
      "vbr": 172.692,
      "vcodec": "avc1.640032",
      "video_ext": "mp4",
      "width": 1920
    },
    {
      "abr": 0,
      "acodec": "none",
      "aspect_ratio": 1.78,
      "audio_ext": "none",
      "dynamic_range": "SDR",
      "ext": "mp4",
      "filesize": null,
      "filesize_approx": 82634845,
      "format": "1080P 高清",
      "format_id": "30077",
      "fps": 30.0,
      "height": 1080,
      "http_headers": {
        "Accept": "text/html,application/xhtml+xml,application/xml;q=0.9,*/*;q=0.8",
        "Accept-Language": "en-us,en;q=0.5",
        "Referer": "https://www.bilibili.com/video/BV1c43zztE6c",
        "Sec-Fetch-Mode": "navigate",
        "User-Agent": "Mozilla/5.0 (Windows NT 10.0; Win64; x64) AppleWebKit/537.36 (KHTML, like Gecko) Chrome/137.0.0.0 Safari/537.36"
      },
      "protocol": "https",
      "quality": 80,
      "resolution": "1920x1080",
      "tbr": 312.136,
      "url": "https://upos-sz-mirrorcosov.bilivideo.com/upgcxcode/50/07/30891180750/30891180750-1-30077.m4s?e=ig8euxZM2rNcNbdlhoNvNC8BqJIzNbfqXBvEqxTEto8BTrNvN0GvT90W5JZMkX_YN0MvXg8gNEV4NC8xNEV4N03eN0B5tZlqNxTEto8BTrNvNeZVuJ10Kj_g2UB02J0mN0B5tZlqNCNEto8BTrNvNC7MTX502C8f2jmMQJ6mqF2fka1mqx6gqj0eN0B599M=&platform=pc&trid=6e6bf5d5356f45b495a7cbdf08b639du&mid=0&deadline=1777954162&nbs=1&oi=2892325852&gen=playurlv3&og=cos&uipk=5&os=cosovbv&upsig=3318bd99946adbe21549745a76f878e5&uparams=e,platform,trid,mid,deadline,nbs,oi,gen,og,uipk,os&bvc=vod&nettype=0&bw=312292&qn_dyeid=6e835943d408cfc200c09dcc69f95152&agrr=0&buvid=6CD6DFCE-00AE-BB7F-293A-E3A9A14863F560854infoc&build=0&dl=0&f=u_0_0&orderid=0,2",
      "vbr": 312.136,
      "vcodec": "hev1.1.6.L150.90",
      "video_ext": "mp4",
      "width": 1920
    },
    {
      "abr": 0,
      "acodec": "none",
      "aspect_ratio": 1.78,
      "audio_ext": "none",
      "dynamic_range": "SDR",
      "ext": "mp4",
      "filesize": null,
      "filesize_approx": 55180791,
      "format": "1080P 高清",
      "format_id": "100026",
      "fps": 30.0,
      "height": 1080,
      "http_headers": {
        "Accept": "text/html,application/xhtml+xml,application/xml;q=0.9,*/*;q=0.8",
        "Accept-Language": "en-us,en;q=0.5",
        "Referer": "https://www.bilibili.com/video/BV1c43zztE6c",
        "Sec-Fetch-Mode": "navigate",
        "User-Agent": "Mozilla/5.0 (Windows NT 10.0; Win64; x64) AppleWebKit/537.36 (KHTML, like Gecko) Chrome/137.0.0.0 Safari/537.36"
      },
      "protocol": "https",
      "quality": 80,
      "resolution": "1920x1080",
      "tbr": 208.434,
      "url": "https://upos-hz-mirrorakam.akamaized.net/upgcxcode/50/07/30891180750/30891180750-1-100026.m4s?e=ig8euxZM2rNcNbdlhoNvNC8BqJIzNbfqXBvEqxTEto8BTrNvN0GvT90W5JZMkX_YN0MvXg8gNEV4NC8xNEV4N03eN0B5tZlqNxTEto8BTrNvNeZVuJ10Kj_g2UB02J0mN0B5tZlqNCNEto8BTrNvNC7MTX502C8f2jmMQJ6mqF2fka1mqx6gqj0eN0B599M=&deadline=1777954162&oi=2892325852&gen=playurlv3&og=hw&platform=pc&trid=6e6bf5d5356f45b495a7cbdf08b639du&mid=0&nbs=1&uipk=5&os=akam&upsig=cd0934471a9aa2c3f1735c75e9f13835&uparams=e,deadline,oi,gen,og,platform,trid,mid,nbs,uipk,os&hdnts=exp=1777954162~hmac=bcddb2a2c3a49dbb44d803b680809ce8ed116ddaf38ada4ad4950aea15525b12&bvc=vod&nettype=0&bw=208545&qn_dyeid=6e835943d408cfc200c09dcc69f95152&agrr=0&buvid=6CD6DFCE-00AE-BB7F-293A-E3A9A14863F560854infoc&build=0&dl=0&f=u_0_0&orderid=0,2",
      "vbr": 208.434,
      "vcodec": "av01.0.00M.10.0.110.01.01.01.0",
      "video_ext": "mp4",
      "width": 1920
    }
  ],
  "fps": 30.0,
  "fulltitle": "川普减税法案：对未来的影响（上）",
  "height": 1080,
  "http_headers": {
    "Referer": "https://www.bilibili.com/video/BV1c43zztE6c"
  },
  "id": "BV1c43zztE6c",
  "language": null,
  "like_count": 5281,
  "original_url": "https://www.bilibili.com/video/BV1c43zztE6c",
  "playlist": null,
  "playlist_index": null,
  "protocol": "https+https",
  "release_year": null,
  "requested_downloads": [
    {
      "__write_download_archive": false,
      "_filename": "川普减税法案：对未来的影响（上） [BV1c43zztE6c].mp4",
      "abr": 184.426,
      "acodec": "mp4a.40.2",
      "aspect_ratio": 1.78,
      "dynamic_range": "SDR",
      "ext": "mp4",
      "filename": "川普减税法案：对未来的影响（上） [BV1c43zztE6c].mp4",
      "filesize_approx": 104005707,
      "format": "1080P 高清+30280 - audio only",
      "format_id": "100026+30280",
      "fps": 30.0,
      "height": 1080,
      "protocol": "https+https",
      "requested_formats": [
        {
          "abr": 0,
          "acodec": "none",
          "aspect_ratio": 1.78,
          "audio_ext": "none",
          "dynamic_range": "SDR",
          "ext": "mp4",
          "filesize": null,
          "filesize_approx": 55180791,
          "format": "1080P 高清",
          "format_id": "100026",
          "fps": 30.0,
          "height": 1080,
          "http_headers": {
            "Accept": "text/html,application/xhtml+xml,application/xml;q=0.9,*/*;q=0.8",
            "Accept-Language": "en-us,en;q=0.5",
            "Referer": "https://www.bilibili.com/video/BV1c43zztE6c",
            "Sec-Fetch-Mode": "navigate",
            "User-Agent": "Mozilla/5.0 (Windows NT 10.0; Win64; x64) AppleWebKit/537.36 (KHTML, like Gecko) Chrome/137.0.0.0 Safari/537.36"
          },
          "protocol": "https",
          "quality": 80,
          "resolution": "1920x1080",
          "tbr": 208.434,
          "url": "https://upos-hz-mirrorakam.akamaized.net/upgcxcode/50/07/30891180750/30891180750-1-100026.m4s?e=ig8euxZM2rNcNbdlhoNvNC8BqJIzNbfqXBvEqxTEto8BTrNvN0GvT90W5JZMkX_YN0MvXg8gNEV4NC8xNEV4N03eN0B5tZlqNxTEto8BTrNvNeZVuJ10Kj_g2UB02J0mN0B5tZlqNCNEto8BTrNvNC7MTX502C8f2jmMQJ6mqF2fka1mqx6gqj0eN0B599M=&deadline=1777954162&oi=2892325852&gen=playurlv3&og=hw&platform=pc&trid=6e6bf5d5356f45b495a7cbdf08b639du&mid=0&nbs=1&uipk=5&os=akam&upsig=cd0934471a9aa2c3f1735c75e9f13835&uparams=e,deadline,oi,gen,og,platform,trid,mid,nbs,uipk,os&hdnts=exp=1777954162~hmac=bcddb2a2c3a49dbb44d803b680809ce8ed116ddaf38ada4ad4950aea15525b12&bvc=vod&nettype=0&bw=208545&qn_dyeid=6e835943d408cfc200c09dcc69f95152&agrr=0&buvid=6CD6DFCE-00AE-BB7F-293A-E3A9A14863F560854infoc&build=0&dl=0&f=u_0_0&orderid=0,2",
          "vbr": 208.434,
          "vcodec": "av01.0.00M.10.0.110.01.01.01.0",
          "video_ext": "mp4",
          "width": 1920
        },
        {
          "abr": 184.426,
          "acodec": "mp4a.40.2",
          "aspect_ratio": null,
          "audio_ext": "m4a",
          "ext": "m4a",
          "filesize": null,
          "filesize_approx": 48824916,
          "format": "30280 - audio only",
          "format_id": "30280",
          "http_headers": {
            "Accept": "text/html,application/xhtml+xml,application/xml;q=0.9,*/*;q=0.8",
            "Accept-Language": "en-us,en;q=0.5",
            "Referer": "https://www.bilibili.com/video/BV1c43zztE6c",
            "Sec-Fetch-Mode": "navigate",
            "User-Agent": "Mozilla/5.0 (Windows NT 10.0; Win64; x64) AppleWebKit/537.36 (KHTML, like Gecko) Chrome/137.0.0.0 Safari/537.36"
          },
          "protocol": "https",
          "resolution": "audio only",
          "tbr": 184.426,
          "url": "https://upos-sz-mirrorcosov.bilivideo.com/upgcxcode/50/07/30891180750/30891180750-1-30280.m4s?e=ig8euxZM2rNcNbdlhoNvNC8BqJIzNbfqXBvEqxTEto8BTrNvN0GvT90W5JZMkX_YN0MvXg8gNEV4NC8xNEV4N03eN0B5tZlqNxTEto8BTrNvNeZVuJ10Kj_g2UB02J0mN0B5tZlqNCNEto8BTrNvNC7MTX502C8f2jmMQJ6mqF2fka1mqx6gqj0eN0B599M=&deadline=1777954162&os=cosovbv&og=hw&uipk=5&oi=2892325852&platform=pc&mid=0&nbs=1&gen=playurlv3&trid=6e6bf5d5356f45b495a7cbdf08b639du&upsig=6192f3ffcc65245e82c09d5122621f30&uparams=e,deadline,os,og,uipk,oi,platform,mid,nbs,gen,trid&bvc=vod&nettype=0&bw=184529&qn_dyeid=6e835943d408cfc200c09dcc69f95152&agrr=0&buvid=6CD6DFCE-00AE-BB7F-293A-E3A9A14863F560854infoc&build=0&dl=0&f=u_0_0&orderid=0,2",
          "vbr": 0,
          "vcodec": "none",
          "video_ext": "none"
        }
      ],
      "resolution": "1920x1080",
      "tbr": 392.86,
      "vbr": 208.434,
      "vcodec": "av01.0.00M.10.0.110.01.01.01.0",
      "width": 1920
    }
  ],
  "requested_formats": [
    {
      "abr": 0,
      "acodec": "none",
      "aspect_ratio": 1.78,
      "audio_ext": "none",
      "dynamic_range": "SDR",
      "ext": "mp4",
      "filesize": null,
      "filesize_approx": 55180791,
      "format": "1080P 高清",
      "format_id": "100026",
      "fps": 30.0,
      "height": 1080,
      "http_headers": {
        "Accept": "text/html,application/xhtml+xml,application/xml;q=0.9,*/*;q=0.8",
        "Accept-Language": "en-us,en;q=0.5",
        "Referer": "https://www.bilibili.com/video/BV1c43zztE6c",
        "Sec-Fetch-Mode": "navigate",
        "User-Agent": "Mozilla/5.0 (Windows NT 10.0; Win64; x64) AppleWebKit/537.36 (KHTML, like Gecko) Chrome/137.0.0.0 Safari/537.36"
      },
      "protocol": "https",
      "quality": 80,
      "resolution": "1920x1080",
      "tbr": 208.434,
      "url": "https://upos-hz-mirrorakam.akamaized.net/upgcxcode/50/07/30891180750/30891180750-1-100026.m4s?e=ig8euxZM2rNcNbdlhoNvNC8BqJIzNbfqXBvEqxTEto8BTrNvN0GvT90W5JZMkX_YN0MvXg8gNEV4NC8xNEV4N03eN0B5tZlqNxTEto8BTrNvNeZVuJ10Kj_g2UB02J0mN0B5tZlqNCNEto8BTrNvNC7MTX502C8f2jmMQJ6mqF2fka1mqx6gqj0eN0B599M=&deadline=1777954162&oi=2892325852&gen=playurlv3&og=hw&platform=pc&trid=6e6bf5d5356f45b495a7cbdf08b639du&mid=0&nbs=1&uipk=5&os=akam&upsig=cd0934471a9aa2c3f1735c75e9f13835&uparams=e,deadline,oi,gen,og,platform,trid,mid,nbs,uipk,os&hdnts=exp=1777954162~hmac=bcddb2a2c3a49dbb44d803b680809ce8ed116ddaf38ada4ad4950aea15525b12&bvc=vod&nettype=0&bw=208545&qn_dyeid=6e835943d408cfc200c09dcc69f95152&agrr=0&buvid=6CD6DFCE-00AE-BB7F-293A-E3A9A14863F560854infoc&build=0&dl=0&f=u_0_0&orderid=0,2",
      "vbr": 208.434,
      "vcodec": "av01.0.00M.10.0.110.01.01.01.0",
      "video_ext": "mp4",
      "width": 1920
    },
    {
      "abr": 184.426,
      "acodec": "mp4a.40.2",
      "aspect_ratio": null,
      "audio_ext": "m4a",
      "ext": "m4a",
      "filesize": null,
      "filesize_approx": 48824916,
      "format": "30280 - audio only",
      "format_id": "30280",
      "http_headers": {
        "Accept": "text/html,application/xhtml+xml,application/xml;q=0.9,*/*;q=0.8",
        "Accept-Language": "en-us,en;q=0.5",
        "Referer": "https://www.bilibili.com/video/BV1c43zztE6c",
        "Sec-Fetch-Mode": "navigate",
        "User-Agent": "Mozilla/5.0 (Windows NT 10.0; Win64; x64) AppleWebKit/537.36 (KHTML, like Gecko) Chrome/137.0.0.0 Safari/537.36"
      },
      "protocol": "https",
      "resolution": "audio only",
      "tbr": 184.426,
      "url": "https://upos-sz-mirrorcosov.bilivideo.com/upgcxcode/50/07/30891180750/30891180750-1-30280.m4s?e=ig8euxZM2rNcNbdlhoNvNC8BqJIzNbfqXBvEqxTEto8BTrNvN0GvT90W5JZMkX_YN0MvXg8gNEV4NC8xNEV4N03eN0B5tZlqNxTEto8BTrNvNeZVuJ10Kj_g2UB02J0mN0B5tZlqNCNEto8BTrNvNC7MTX502C8f2jmMQJ6mqF2fka1mqx6gqj0eN0B599M=&deadline=1777954162&os=cosovbv&og=hw&uipk=5&oi=2892325852&platform=pc&mid=0&nbs=1&gen=playurlv3&trid=6e6bf5d5356f45b495a7cbdf08b639du&upsig=6192f3ffcc65245e82c09d5122621f30&uparams=e,deadline,os,og,uipk,oi,platform,mid,nbs,gen,trid&bvc=vod&nettype=0&bw=184529&qn_dyeid=6e835943d408cfc200c09dcc69f95152&agrr=0&buvid=6CD6DFCE-00AE-BB7F-293A-E3A9A14863F560854infoc&build=0&dl=0&f=u_0_0&orderid=0,2",
      "vbr": 0,
      "vcodec": "none",
      "video_ext": "none"
    }
  ],
  "requested_subtitles": null,
  "resolution": "1920x1080",
  "stretched_ratio": null,
  "subtitles": {},
  "tags": [
    "硬核财经知识必看",
    "川普",
    "美国",
    "财经",
    "金融",
    "大而美",
    "特朗普",
    "减税",
    "大漂亮",
    "青年用「财」图鉴7.0"
  ],
  "tbr": 392.86,
  "thumbnail": "http://i0.hdslb.com/bfs/archive/e06afbb30ed811e7c7f07c7ed7deeb406c5e3dff.jpg",
  "thumbnails": [
    {
      "id": "0",
      "url": "http://i0.hdslb.com/bfs/archive/e06afbb30ed811e7c7f07c7ed7deeb406c5e3dff.jpg"
    }
  ],
  "timestamp": 1751835072,
  "title": "川普减税法案：对未来的影响（上）",
  "upload_date": "20250706",
  "uploader": "战国时代_姜汁汽水",
  "uploader_id": "1039025435",
  "vbr": 208.434,
  "vcodec": "av01.0.00M.10.0.110.01.01.01.0",
  "view_count": 194799,
  "webpage_url": "https://www.bilibili.com/video/BV1c43zztE6c",
  "webpage_url_basename": "BV1c43zztE6c",
  "webpage_url_domain": "bilibili.com",
  "width": 1920
}
